scidata/__init__.py
scidata-0.1.1.dist-info/LICENSE
scidata-0.1.1.dist-info/WHEEL
scidata-0.1.1.dist-info/METADATA
scidata-0.1.1.dist-info/RECORD
