Metadata-Version: 2.1
Name: scidata
Version: 0.1.1
Summary: scidata.
Author-email: Lamin Labs <laminlabs@gmail.com>
Classifier: License :: OSI Approved :: MIT License
Project-URL: Home, https://github.com/laminlabs/scidata
